ncp_wrapper/__init__.py
ncp_wrapper/naver_works.py
ncp_wrapper-0.0.2.dist-info/LICENSE
ncp_wrapper-0.0.2.dist-info/METADATA
ncp_wrapper-0.0.2.dist-info/WHEEL
ncp_wrapper-0.0.2.dist-info/top_level.txt
ncp_wrapper-0.0.2.dist-info/RECORD
