Metadata-Version: 2.1
Name: ncp_wrapper
Version: 0.0.2
Summary: Naver Cloud Platform Helper Classes and Methods
Author-email: Jeongjin Kim <thefuturecreator@gmail.com>
Project-URL: Homepage, https://github.com/thecodinglog/ncp
Project-URL: Bug Tracker, https://github.com/thecodinglog/ncp/issues
Classifier: Programming Language :: Python :: 3
Classifier: License :: OSI Approved :: MIT License
Classifier: Operating System :: OS Independent
Requires-Python: >=3.7
License-File: LICENSE
